pingcord/__init__.py
pingcord/cli.py
pingcord-0.1.0.dist-info/licenses/LICENSE
pingcord-0.1.0.dist-info/METADATA
pingcord-0.1.0.dist-info/WHEEL
pingcord-0.1.0.dist-info/entry_points.txt
pingcord-0.1.0.dist-info/top_level.txt
pingcord-0.1.0.dist-info/RECORD
