Metadata-Version: 2.4
Name: pingcord
Version: 0.1.0
Summary: Send shell command output to Discord using webhooks.
Home-page: https://github.com/theo-vdml/pingcord
Author: theo_vdml
License: MIT
Classifier: Programming Language :: Python :: 3
Classifier: License :: OSI Approved :: MIT License
Classifier: Operating System :: OS Independent
Requires-Python: >=3.7
License-File: LICENSE
Requires-Dist: requests>=2.0.0
Requires-Dist: pyyaml>=6.0
Dynamic: author
Dynamic: classifier
Dynamic: description
Dynamic: description-content-type
Dynamic: home-page
Dynamic: license
Dynamic: license-file
Dynamic: requires-dist
Dynamic: requires-python
Dynamic: summary
